FlamingoBaryonResponseEmulator/__init__.py
FlamingoBaryonResponseEmulator/__version__.py
FlamingoBaryonResponseEmulator/flamingo_response_emulator.py
FlamingoBaryonResponseEmulator/data/emulator.xz
flamingobaryonresponseemulator-1.1.0.dist-info/METADATA
flamingobaryonresponseemulator-1.1.0.dist-info/WHEEL
flamingobaryonresponseemulator-1.1.0.dist-info/top_level.txt
flamingobaryonresponseemulator-1.1.0.dist-info/RECORD
