Metadata-Version: 2.4
Name: FlamingoBaryonResponseEmulator
Version: 1.1.0
Summary: A Gaussian process emulator predicting the baryonic response for a range of wavelengths, redshifts, and galaxy formation model trained on the FLAMINGO suite of simulations.
Author-email: Matthieu Schaller <matthieu.schaller@gmail.com>
Project-URL: Homepage, https://github.com/FLAMINGOSIM/FlamingoBaryonResponseEmulator
Classifier: Programming Language :: Python :: 3.10
Classifier: Programming Language :: Python :: 3.11
Classifier: Programming Language :: Python :: 3.12
Classifier: Programming Language :: Python :: 3.13
Classifier: License :: OSI Approved :: GNU Lesser General Public License v3 or later (LGPLv3+)
Classifier: Operating System :: OS Independent
Requires-Python: >3.10.0
Requires-Dist: numpy
Requires-Dist: scipy
Requires-Dist: swiftemulator
Requires-Dist: george
